odoo/addons/account_move_exception/README.rst
odoo/addons/account_move_exception/__init__.py
odoo/addons/account_move_exception/__manifest__.py
odoo/addons/account_move_exception/init_hook.py
odoo/addons/account_move_exception/data/account_exception_data.xml
odoo/addons/account_move_exception/i18n/account_move_exception.pot
odoo/addons/account_move_exception/models/__init__.py
odoo/addons/account_move_exception/models/account_move.py
odoo/addons/account_move_exception/models/account_move_line.py
odoo/addons/account_move_exception/models/exception_rule.py
odoo/addons/account_move_exception/readme/CONTRIBUTORS.rst
odoo/addons/account_move_exception/readme/DESCRIPTION.rst
odoo/addons/account_move_exception/readme/USAGE.rst
odoo/addons/account_move_exception/static/description/icon.png
odoo/addons/account_move_exception/static/description/index.html
odoo/addons/account_move_exception/tests/__init__.py
odoo/addons/account_move_exception/tests/test_account_exception.py
odoo/addons/account_move_exception/views/account_view.xml
odoo/addons/account_move_exception/wizard/__init__.py
odoo/addons/account_move_exception/wizard/account_exception_confirm.py
odoo/addons/account_move_exception/wizard/account_exception_confirm_view.xml
odoo13_addon_account_move_exception-13.0.1.0.1.dist-info/METADATA
odoo13_addon_account_move_exception-13.0.1.0.1.dist-info/WHEEL
odoo13_addon_account_move_exception-13.0.1.0.1.dist-info/top_level.txt
odoo13_addon_account_move_exception-13.0.1.0.1.dist-info/RECORD
